<?xml version="1.0" encoding="UTF-8" ?>
<!DOCTYPE mapper PUBLIC "-//mybatis.org//DTD Mapper 3.0//EN" "http://mybatis.org/dtd/mybatis-3-mapper.dtd" >
<mapper namespace="com.ev.dao.SysRoleDao">
    <!--auto generated Code-->
    <resultMap id="AllColumnMap" type="com.ev.entity.SysRole">
        <result column="role_id" property="roleId"/>
        <result column="role_name" property="roleName"/>
        <result column="remark" property="remark"/>
    </resultMap>

    <!--auto generated Code-->
    <sql id="all_column">
        `role_id`,
        `role_name`,
        `remark`
    </sql>

    <!--auto generated Code-->
    <insert id="insert" useGeneratedKeys="true" keyProperty="pojo.roleId">
        INSERT INTO sys_role (
            `role_id`,
            `role_name`,
            `remark`
        ) VALUES (
            #{pojo.roleId},
            #{pojo.roleName},
            #{pojo.remark}
        )
    </insert>

    <!--auto generated Code-->
    <insert id="insertSelective" useGeneratedKeys="true" keyProperty="pojo.roleId">
        INSERT INTO sys_role
        <trim prefix="(" suffix=")" suffixOverrides=",">
            <if test="pojo.roleId!=null"> `role_id`,</if>
            <if test="pojo.roleName!=null"> `role_name`,</if>
            <if test="pojo.remark!=null"> `remark`,</if>
        </trim>
        VALUES
        <trim prefix="(" suffix=")" suffixOverrides=",">
            <if test="pojo.roleId!=null">#{pojo.roleId},</if>
            <if test="pojo.roleName!=null">#{pojo.roleName},</if>
            <if test="pojo.remark!=null">#{pojo.remark},</if>
        </trim>
    </insert>

    <!--auto generated Code-->
    <insert id="insertList">
        INSERT INTO sys_role (
        <include refid="all_column"/>
        )VALUES
        <foreach collection="pojos" item="pojo" index="index" separator=",">
            (
            #{pojo.roleId},
            #{pojo.roleName},
            #{pojo.remark}
            )
        </foreach>
    </insert>

    <!--auto generated Code-->
    <update id="update">
        UPDATE sys_role
        <set>
            <if test="pojo.roleId != null"> `role_id` = #{pojo.roleId}, </if>
            <if test="pojo.roleName != null"> `role_name` = #{pojo.roleName}, </if>
            <if test="pojo.remark != null"> `remark` = #{pojo.remark} </if>
        </set>
        WHERE role_id = #{pojo.roleId}
    </update>

<!--auto generated by codehelper on 2019-01-26 21:17:17-->
    <select id="findbyRoleIdAndRoleNameIn" resultMap="AllColumnMap">
        select
        <include refid="all_column"/>
        from sys_role
        where `role_id`=#{roleId} and `role_name` in
        <foreach item="item" index="index" collection="roleNameList"
                 open="(" separator="," close=")">
            #{item}
        </foreach>
    </select>

<!--auto generated by codehelper on 2019-02-15 14:58:11-->
    <select id="findRoleName" resultType="java.lang.String">
        select `role_name`
        from sys_role
    </select>



<!--auto generated by codehelper on 2019-02-25 17:59:14-->
    <select id="findRoleIdAndRemark" resultMap="AllColumnMap">
        select `role_id`, `remark`
        from sys_role
    </select>

<!--auto generated by codehelper on 2019-03-03 11:44:15-->
    <select id="find" resultMap="AllColumnMap">
        select
        <include refid="all_column"/>
        from sys_role
    </select>

<!--auto generated by codehelper on 2019-03-03 23:36:29-->
    <delete id="deleteByRoleId">
        delete from sys_role
        where `role_id`=#{roleId}
    </delete>

<!--auto generated by codehelper on 2019-03-03 23:53:04-->
    <select id="findByRoleId" resultMap="AllColumnMap">
        select
        <include refid="all_column"/>
        from sys_role
        where `role_id`=#{roleId}
    </select>

</mapper>

